Metadata-Version: 1.2
Name: eeg
Version: 0.6
Summary: EEG
Home-page: UNKNOWN
Author: Yeison Cardona
Author-email: yeisoneng@gmail.com
Maintainer: Yeison Cardona
Maintainer-email: yeisoneng@gmail.com
License: BSD License
Download-URL: https://bitbucket.org/gcpds/python-eeg/downloads/
Platform: UNKNOWN
